nrel_rev-0.14.5.dist-info/licenses/LICENSE
reV/__init__.py
reV/cli.py
reV/version.py
reV/SAM/SAM.py
reV/SAM/__init__.py
reV/SAM/defaults.py
reV/SAM/econ.py
reV/SAM/generation.py
reV/SAM/version_checker.py
reV/SAM/windbos.py
reV/SAM/defaults/USA AZ Phoenix Sky Harbor Intl Ap (TMY3).csv
reV/SAM/defaults/USA CA Daggett (TMY2).csv
reV/SAM/defaults/US_Wave.csv
reV/SAM/defaults/WY Southern-Flat Lands.srw
reV/SAM/defaults/geothermal.json
reV/SAM/defaults/i_pvwattsv5.json
reV/bespoke/__init__.py
reV/bespoke/bespoke.py
reV/bespoke/cli_bespoke.py
reV/bespoke/gradient_free.py
reV/bespoke/pack_turbs.py
reV/bespoke/place_turbines.py
reV/config/__init__.py
reV/config/base_analysis_config.py
reV/config/base_config.py
reV/config/cli_project_points.py
reV/config/curtailment.py
reV/config/execution.py
reV/config/output_request.py
reV/config/project_points.py
reV/config/sam_config.py
reV/econ/__init__.py
reV/econ/cli_econ.py
reV/econ/econ.py
reV/econ/economies_of_scale.py
reV/econ/utilities.py
reV/generation/__init__.py
reV/generation/base.py
reV/generation/cli_gen.py
reV/generation/generation.py
reV/generation/output_attributes/generation.json
reV/generation/output_attributes/lcoe_fcr.json
reV/generation/output_attributes/lcoe_fcr_inputs.json
reV/generation/output_attributes/linear_fresnel.json
reV/generation/output_attributes/other.json
reV/generation/output_attributes/single_owner.json
reV/generation/output_attributes/solar_water_heat.json
reV/generation/output_attributes/trough_heat.json
reV/generation/output_attributes/windbos.json
reV/handlers/__init__.py
reV/handlers/cli_collect.py
reV/handlers/cli_multi_year.py
reV/handlers/exclusions.py
reV/handlers/multi_year.py
reV/handlers/outputs.py
reV/handlers/transmission.py
reV/hybrids/__init__.py
reV/hybrids/cli_hybrids.py
reV/hybrids/hybrid_methods.py
reV/hybrids/hybrids.py
reV/losses/__init__.py
reV/losses/power_curve.py
reV/losses/scheduled.py
reV/losses/utils.py
reV/nrwal/__init__.py
reV/nrwal/cli_nrwal.py
reV/nrwal/nrwal.py
reV/qa_qc/__init__.py
reV/qa_qc/cli_qa_qc.py
nrel_rev-0.14.5.dist-info/METADATA
nrel_rev-0.14.5.dist-info/WHEEL
nrel_rev-0.14.5.dist-info/entry_points.txt
nrel_rev-0.14.5.dist-info/top_level.txt
nrel_rev-0.14.5.dist-info/RECORD
