Metadata-Version: 2.4
Name: NREL-reV
Version: 0.14.5
Summary: National Renewable Energy Laboratory's (NREL's) Renewable Energy Potential(V) Model: reV
Author-email: Galen Maclaurin <galen.maclaurin@nrel.gov>
Maintainer-email: Grant Buster <gbuster@nrel.gov>, Paul Pinchuk <ppinchuk@nrel.gov>
License-Expression: BSD-3-Clause
Project-URL: homepage, https://www2.nrel.gov/gis/renewable-energy-potential
Project-URL: documentation, https://nrel.github.io/reV/
Project-URL: repository, https://github.com/NREL/reV
Keywords: reV,NREL
Classifier: Development Status :: 4 - Beta
Classifier: Intended Audience :: Science/Research
Classifier: Natural Language :: English
Classifier: Programming Language :: Python :: 3.9
Classifier: Programming Language :: Python :: 3.10
Classifier: Programming Language :: Python :: 3.11
Classifier: Programming Language :: Python :: 3.12
Classifier: Programming Language :: Python :: 3.13
Requires-Python: >=3.9
License-File: LICENSE
Requires-Dist: NREL-gaps>=0.8.0
Requires-Dist: NREL-NRWAL>=0.0.11
Requires-Dist: NREL-PySAM~=7.0.0
Requires-Dist: NREL-rex>=0.4.0
Requires-Dist: numpy<3,>=2.0.2
Requires-Dist: packaging<25,>=24.2
Requires-Dist: plotly<7,>=6.0.1
Requires-Dist: plotting<0.1,>=0.0.7
Requires-Dist: shapely<3,>=2.0.7
Provides-Extra: test
Requires-Dist: pytest<9,>=8.4.0; extra == "test"
Provides-Extra: dev
Requires-Dist: flake8; extra == "dev"
Requires-Dist: pre-commit; extra == "dev"
Requires-Dist: pylint; extra == "dev"
Provides-Extra: hsds
Requires-Dist: hsds<1,>=0.8.4; extra == "hsds"
Provides-Extra: build
Requires-Dist: build<2,>=1.2.2; extra == "build"
Requires-Dist: pkginfo<2,>=1.10.0; extra == "build"
Requires-Dist: twine<7,>=6.1.0; extra == "build"
Dynamic: license-file
